Workbook

Sheet Summary
B2: Chaos Ransomware – Data Leak Site Victim Snapshot
B3: Source: Chaos DLS API (/api/post/list + /api/post/get), collected via Tor. Prepared for SC4016 coursework.
B5: Snapshot date (UTC) | C5: 46297 | D5: ← date the scrape was run; drives Expired/Pending status
B7: Key Figures
B8: Published victims (named) | C8: =COUNTA('Published Victims'!B2:B84) -> 83
B9: Pending posts (countdown, name hidden) | C9: =COUNTA('Pending (Obfuscated)'!B2:B44) -> 43
B10: of which still pending at snapshot | C10: =COUNTIF('Pending (Obfuscated)'!E2:E44,"Pending") -> 41
B11: Total posts on site | C11: =C8+C9 -> 126
B12: Total claimed leaked data – published (GB) | C12: =SUM('Published Victims'!F2:F84) -> 37983
B13: Total claimed leaked data – published (TB) | C13: =C12/1000 -> 37.983
B14: Average claimed size per published victim (GB) | C14: =AVERAGEIF('Published Victims'!F2:F84,">0") -> 474.7875
B15: Largest single claimed leak (GB) | C15: =MAX('Published Victims'!F2:F84) -> 3200
B16: Largest leak – victim | C16: =INDEX('Published Victims'!B2:B84,MATCH(C15,'Published Victims'!F2:F84,0)) -> horizonmedia.com
B17: Most-viewed victim post | C17: =INDEX('Published Victims'!B2:B84,MATCH(MAX('Published Victims'!G2:G84),'Published Victims'!G2:G84,0)) -> archway.com
B18: Victims in USA (% of published) | C18: =COUNTIF('Published Victims'!E2:E84,"USA")/C8 -> 0.74698795
B21: Victims by Sector (published) | G21: Victims by Country (published)
B22: Sector | C22: Victims | D22: % of Published | E22: Claimed GB | G22: Country | H22: Victims | I22: % of Published
B23: Manufacturing | C23: =COUNTIF('Published Victims'!$D$2:$D$84,B23) -> 17 | D23: =C23/$C$8 -> 0.20481928 | E23: =SUMIF('Published Victims'!$D$2:$D$84,B23,'Published Victims'!$F$2:$F$84) -> 6963 | G23: USA | H23: =COUNTIF('Published Victims'!$E$2:$E$84,G23) -> 62 | I23: =H23/$C$8 -> 0.74698795
B24: Healthcare & Pharma | C24: =COUNTIF('Published Victims'!$D$2:$D$84,B24) -> 12 | D24: =C24/$C$8 -> 0.14457831 | E24: =SUMIF('Published Victims'!$D$2:$D$84,B24,'Published Victims'!$F$2:$F$84) -> 5929 | G24: Canada | H24: =COUNTIF('Published Victims'!$E$2:$E$84,G24) -> 10 | I24: =H24/$C$8 -> 0.12048193
B25: Construction & Engineering | C25: =COUNTIF('Published Victims'!$D$2:$D$84,B25) -> 11 | D25: =C25/$C$8 -> 0.13253012 | E25: =SUMIF('Published Victims'!$D$2:$D$84,B25,'Published Victims'!$F$2:$F$84) -> 5970 | G25: UK | H25: =COUNTIF('Published Victims'!$E$2:$E$84,G25) -> 3 | I25: =H25/$C$8 -> 0.036144578
B26: Transportation & Logistics | C26: =COUNTIF('Published Victims'!$D$2:$D$84,B26) -> 9 | D26: =C26/$C$8 -> 0.10843373 | E26: =SUMIF('Published Victims'!$D$2:$D$84,B26,'Published Victims'!$F$2:$F$84) -> 3480 | G26: Unknown | H26: =COUNTIF('Published Victims'!$E$2:$E$84,G26) -> 3 | I26: =H26/$C$8 -> 0.036144578
B27: Business & Professional Services | C27: =COUNTIF('Published Victims'!$D$2:$D$84,B27) -> 6 | D27: =C27/$C$8 -> 0.072289157 | E27: =SUMIF('Published Victims'!$D$2:$D$84,B27,'Published Victims'!$F$2:$F$84) -> 5290 | G27: Austria | H27: =COUNTIF('Published Victims'!$E$2:$E$84,G27) -> 1 | I27: =H27/$C$8 -> 0.012048193
B28: Retail & Consumer | C28: =COUNTIF('Published Victims'!$D$2:$D$84,B28) -> 6 | D28: =C28/$C$8 -> 0.072289157 | E28: =SUMIF('Published Victims'!$D$2:$D$84,B28,'Published Victims'!$F$2:$F$84) -> 3090 | G28: Germany | H28: =COUNTIF('Published Victims'!$E$2:$E$84,G28) -> 1 | I28: =H28/$C$8 -> 0.012048193
B29: Technology | C29: =COUNTIF('Published Victims'!$D$2:$D$84,B29) -> 5 | D29: =C29/$C$8 -> 0.060240964 | E29: =SUMIF('Published Victims'!$D$2:$D$84,B29,'Published Victims'!$F$2:$F$84) -> 2040 | G29: Italy | H29: =COUNTIF('Published Victims'!$E$2:$E$84,G29) -> 1 | I29: =H29/$C$8 -> 0.012048193
B30: Automotive | C30: =COUNTIF('Published Victims'!$D$2:$D$84,B30) -> 4 | D30: =C30/$C$8 -> 0.048192771 | E30: =SUMIF('Published Victims'!$D$2:$D$84,B30,'Published Victims'!$F$2:$F$84) -> 648 | G30: Sweden | H30: =COUNTIF('Published Victims'!$E$2:$E$84,G30) -> 1 | I30: =H30/$C$8 -> 0.012048193
B31: Chemicals | C31: =COUNTIF('Published Victims'!$D$2:$D$84,B31) -> 4 | D31: =C31/$C$8 -> 0.048192771 | E31: =SUMIF('Published Victims'!$D$2:$D$84,B31,'Published Victims'!$F$2:$F$84) -> 1195 | G31: Taiwan | H31: =COUNTIF('Published Victims'!$E$2:$E$84,G31) -> 1 | I31: =H31/$C$8 -> 0.012048193
B32: Financial Services & Insurance | C32: =COUNTIF('Published Victims'!$D$2:$D$84,B32) -> 4 | D32: =C32/$C$8 -> 0.048192771 | E32: =SUMIF('Published Victims'!$D$2:$D$84,B32,'Published Victims'!$F$2:$F$84) -> 1912 | G32: Total | H32: =SUM(H23:H31) -> 83
B33: Energy & Materials | C33: =COUNTIF('Published Victims'!$D$2:$D$84,B33) -> 3 | D33: =C33/$C$8 -> 0.036144578 | E33: =SUMIF('Published Victims'!$D$2:$D$84,B33,'Published Victims'!$F$2:$F$84) -> 1210
B34: Non-profit | C34: =COUNTIF('Published Victims'!$D$2:$D$84,B34) -> 1 | D34: =C34/$C$8 -> 0.012048193 | E34: =SUMIF('Published Victims'!$D$2:$D$84,B34,'Published Victims'!$F$2:$F$84) -> 0
B35: Real Estate | C35: =COUNTIF('Published Victims'!$D$2:$D$84,B35) -> 1 | D35: =C35/$C$8 -> 0.012048193 | E35: =SUMIF('Published Victims'!$D$2:$D$84,B35,'Published Victims'!$F$2:$F$84) -> 256
B36: Total | C36: =SUM(C23:C35) -> 83 | D36: =SUM(D23:D35) -> 1 | E36: =SUM(E23:E35) -> 37983

Sheet Published Victims
A1: # | B1: Victim | C1: Domain | D1: Sector (inferred) | E1: Country (inferred) | F1: Claimed Leak Size (GB) | G1: Site Views | H1: Reference Website | I1: Leak Post Description (excerpt) | J1: Leak Post URL
A2: 1 | B2: advantech.com | C2: advantech.com | D2: Technology | E2: Taiwan | F2: 500 | G2: 2368 | H2: https://www.zoominfo.com/c/advantech-co-ltd/1149499 | I2: We are publishing 5% of the total data because the company's management is ignoring the situation and has not contacted us. The company's management has exactly 48 hours to contact us; otherwise, the entire dataset will be published. | J2: http://hptqq2o2qjva7lcaaq67w36jihzivkaitkexorauw7b2yul2z6zozpqd.onion/Pfa5mOakuACFbqhsUgrEzO57i8E7T5gR/advantech-com
A3: 2 | B3: steelhausinc.com | C3: steelhausinc.com | D3: Manufacturing | E3: Unknown | F3: 152 | G3: 20001 | H3: https://www.zoominfo.com/c/steelhaus-technologies-inc/345554973 | I3: Steelhaus boldly drives the market with innovative energy solutions; fusing practical, field proven experience, adaptable engineering, integrated manufacturing, and uncompromising safety with relentless delivery of unwavering customer service | J3: http://hptqq2o2qjva7lcaaq67w36jihzivkaitkexorauw7b2yul2z6zozpqd.onion/sZnWPIpfhHl0hrPEjKO92RbmEwS5hdiG/steelhausinc-com
A4: 3 | B4: glasfloss.com | C4: glasfloss.com | D4: Manufacturing | E4: USA | F4: 402 | G4: 19516 | H4: https://www.zoominfo.com/c/glasfloss-industries-inc/16072811 | I4: Glasfloss Industries manufactures and supplies HVAC air filtration products for industrial, commercial, and residential applications. The company was founded in 1936 and is headquartered in DeSoto, Texas | J4: http://hptqq2o2qjva7lcaaq67w36jihzivkaitkexorauw7b2yul2z6zozpqd.onion/pAbOCSoJdOztVDgF8uBcq7FY0fsqN6J4/glasfloss-com
A5: 4 | B5: copeplastics.com | C5: copeplastics.com | D5: Manufacturing | E5: USA | F5: 57 | G5: 27688 | H5: https://www.zoominfo.com/c/cope-plastics-inc/29364532 | I5: Cope Plastics is a leading U.S. distributor and fabricator of performance plastics, serving industrial and commercial customers since 1946. From our headquarters in Alton, Illinois and through multiple branch locations, we support clients across countless sectorsheavy equipment, transportation, aero… | J5: http://hptqq2o2qjva7lcaaq67w36jihzivkaitkexorauw7b2yul2z6zozpqd.onion/8q2RrLiN6uJyo3CWGnW7QE1SXOQCfPCb/copeplastics-com
A6: 5 | B6: carolinaasthma.com | C6: carolinaasthma.com | D6: Healthcare & Pharma | E6: USA | F6: 290 | G6: 2662 | H6: https://www.zoominfo.com/c/carolina-asthma--allergy-center-pa/36772468 | I6: Carolina Asthma & Allergy Center is the largest asthma and allergy practice in the Charlotte area, staffed entirely by board-certified physicians. They offer a comprehensive range of services including allergy testing, asthma management, and specialized treatments for various allergic conditions. Th… | J6: http://hptqq2o2qjva7lcaaq67w36jihzivkaitkexorauw7b2yul2z6zozpqd.onion/EBMAw6xdj4wpIEZoORa8EhwkJcBfURKu/carolinaasthma-com
A7: 6 | B7: parkdental.com | C7: parkdental.com | D7: Healthcare & Pharma | E7: USA | F7: 275 | G7: 305 | H7: https://www.zoominfo.com/c/park-dental/81691770 | I7: To the Management of Park Dental: Time is running out. Our previous attempts to establish a constructive dialogue regarding the security breach have been met with silence. If the management of Park Dental fails to get in touch with our team within the next 24 hours, we will proceed with the full p… | J7: http://hptqq2o2qjva7lcaaq67w36jihzivkaitkexorauw7b2yul2z6zozpqd.onion/HPqaxQyDu2b5XtxY8Z4HTe0Jgz6j1PsS/parkdental-com
A8: 7 | B8: macallister.com | C8: macallister.com | D8: Construction & Engineering | E8: USA | F8: 75 | G8: 42596 | H8: https://www.zoominfo.com/c/macallister-machinery-co-inc/41109495 | I8: Founded in 1945 and headquartered in Indianapolis, Indiana, MacAllister Machinery Co., Inc. is a construction and heavy equipment dealer for Caterpillar | J8: http://hptqq2o2qjva7lcaaq67w36jihzivkaitkexorauw7b2yul2z6zozpqd.onion/HWYpccK3tQd2VIazsCSTQ72a2gcLaAhr/macallister-com
A9: 8 | B9: corematerials.com | C9: corematerials.com | D9: Manufacturing | E9: USA | F9: 105 | G9: 41302 | H9: https://www.zoominfo.com/c/core-molding-technologies/34509611 | I9: Core Molding Technologies, Inc. is an engineered materials manufacturer specializing in thermoplastic and thermoset molded structural products. The company provides advanced composite molding solutions for the transportation, building products, utilities, powersports, marine, automotive, agriculture… | J9: http://hptqq2o2qjva7lcaaq67w36jihzivkaitkexorauw7b2yul2z6zozpqd.onion/Y1fpWBmDHkS9UVcAr34ryui3hKyJrn7R/corematerials-com
A10: 9 | B10: artiflexmfg.com | C10: artiflexmfg.com | D10: Manufacturing | E10: USA | F10: 1200 | G10: 23711 | H10: https://www.zoominfo.com/c/artiflex-manufacturing-llc/347538637 | I10: ArtiFlex Manufacturing LLC operates as a specialized contract manufacturer focused on delivering precision sheet metal solutions to diverse industrial sectors. The company has built its operational foundation on deep expertise in manufacturing engineering, combining technical knowledge with practica… | J10: http://hptqq2o2qjva7lcaaq67w36jihzivkaitkexorauw7b2yul2z6zozpqd.onion/PzfXqKW5FK3vzC3lKchrNzIU8vn32VKA/artiflexmfg-com
A11: 10 | B11: mankatoclinic.com | C11: mankatoclinic.com | D11: Healthcare & Pharma | E11: USA | F11: 610 | G11: 23793 | H11: https://www.zoominfo.com/c/mankato-clinic-ltd/69946466 | I11: The Mankato Clinic was founded Mankato, Minnesota in 1916, by five area physicians who believed that a comprehensive, multi-specialty group practice offered the best means of providing quality health care to the residents of southern Minnesota. The mission of the Mankato Clinic is to improve the hea… | J11: http://hptqq2o2qjva7lcaaq67w36jihzivkaitkexorauw7b2yul2z6zozpqd.onion/Rct2l4z0PDB9rUIwh31yc0cSk5utsqfl/mankatoclinic-com
A12: 11 | B12: mswalker.com | C12: mswalker.com | D12: Retail & Consumer | E12: USA | F12: 620 | G12: 44722 | H12: https://www.zoominfo.com/c/ms-walker-inc/80759113 | I12: M.S. Walker is a wholesale distributor of wines and spirits. This company is headquartered in Norwood, Massachusetts and was founded in 1933 | J12: http://hptqq2o2qjva7lcaaq67w36jihzivkaitkexorauw7b2yul2z6zozpqd.onion/P59trLgiyhDHkPQY7RaQtsRxbtuwI281/mswalker-com
A13: 12 | B13: parkderochie.com | C13: parkderochie.com | D13: Construction & Engineering | E13: Canada | F13: 910 | G13: 44694 | H13: https://www.zoominfo.com/c/park-derochie-coatings-ltd/90424117 | I13: Park Derochie (part of PD Group) is a leading Canadian contractor specializing in industrial coatings, fireproofing, scaffolding, insulation, and related services for large-scale infrastructure and industrial projects. The company supports sectors such as oil and gas, petrochemical, mining, utilitie… | J13: http://hptqq2o2qjva7lcaaq67w36jihzivkaitkexorauw7b2yul2z6zozpqd.onion/BrCvLMvN3dvI4pQ09PPTXcUiv8IhkOOJ/parkderochie-com
... A29: 28 | B29: roofdepot.com | C29: roofdepot.com | D29: Construction & Engineering | E29: USA | F29: 115 | G29: 121084 | H29: https://www.zoominfo.com/c/roof-depot-inc/348637856 | I29: Founded in 1998 and headquartered in Alpharetta, GA, Roof Depot is a roofing manufacturer that specializes in roof installation, repairs & replacement | J29: http://hptqq2o2qjva7lcaaq67w36jihzivkaitkexorauw7b2yul2z6zozpqd.onion/uLzP0TsDiuseR83BjARDFmCrKPkiFuuX/roofdepot-com
A30: 29 | B30: ingerman.com | C30: ingerman.com | D30: Real Estate | E30: USA | F30: 256 | G30: 119366 | I30: Ingerman is a developer, builder and manager of multifamily housing communities throughout the Mid-Atlantic region. | J30: http://hptqq2o2qjva7lcaaq67w36jihzivkaitkexorauw7b2yul2z6zozpqd.onion/eFnDbkPSi9k9g3lgEso7e118pg6iqv7A/ingerman-com
A31: 30 | B31: sleemanbreweries.ca | C31: sleemanbreweries.ca | D31: Retail & Consumer | E31: Canada | F31: 420 | G31: 97132 | H31: http://www.sleemanbreweries.ca | I31: Sleeman Breweries was founded in 1851 and headquartered in Guelph, Ontario. The company now markets and distributes world-class domestic and imported products. | J31: http://hptqq2o2qjva7lcaaq67w36jihzivkaitkexorauw7b2yul2z6zozpqd.onion/R0byD7G28XKZ01jkwCt9ZUgufBzfVnTA/sleemanbreweries-ca
A32: 31 | B32: graymont.com | C32: graymont.com | D32: Energy & Materials | E32: Canada | F32: 400 | G32: 124018 | I32: NOTICE REGARDING GRAYMONT.COM We are officially announcing that our negotiations with Graymont regarding the security of their data assets have been terminated. Despite our repeated attempts to reach a professional agreement, Graymont’s management has demonstrated a profound lack of understandin… | J32: http://hptqq2o2qjva7lcaaq67w36jihzivkaitkexorauw7b2yul2z6zozpqd.onion/EZcDDIMSEXtpnWM0AeLwoEfoorKZ9ZyM/graymont-com
A33: 32 | B33: gisy.com | C33: gisy.com | D33: Transportation & Logistics | E33: USA | F33: 1100 | G33: 107172 | H33: https://www.zoominfo.com/c/grand-isle-shipyard-inc/50466057 | I33: [FINAL LEAK NOTICE] Target: gisy.com Status: Negotiation Failure / Full Data Disclosure Archive: 1.1 TB / 341,712 files Global Industries has officially chosen to ignore our ultimatum regarding the security of their data. Despite the sensitivity of the information in our possession, their leadersh… | J33: http://hptqq2o2qjva7lcaaq67w36jihzivkaitkexorauw7b2yul2z6zozpqd.onion/HvNtlUrCy28pkleddtj1Ndi2vRGIEVRM/gisy-com
A34: 33 | B34: airespring.com | C34: airespring.com | D34: Technology | E34: USA | F34: 140 | G34: 136012 | H34: https://www.zoominfo.com/c/airespring-inc/5739766 | I34: Founded in 2001, AireSpring is a Managed Services Provider specializing in Unified Communications, Managed Network, and IT Services, serving thousands of businesses nationwide. AireSpring provides fully managed and connected end-to-end, next-generation solutions for multi-location enterprise custome… | J34: http://hptqq2o2qjva7lcaaq67w36jihzivkaitkexorauw7b2yul2z6zozpqd.onion/oMJZD5nwXI71QbElAkvd2L28Fb4xbKRk/airespring-com
A35: 34 | B35: randa.net | C35: randa.net | D35: Retail & Consumer | E35: USA | F35: 750 | G35: 121966 | H35: http://www.randa.net | I35: Randa Apparel & Accessories is a global powerhouse and one of the world's leading apparel and lifestyle accessories companies, headquartered in New York City at 417 Fifth Avenue, 11th Floor. Founded in 1910, with the founder's family having been in the neckwear business since that time and the curre… | J35: http://hptqq2o2qjva7lcaaq67w36jihzivkaitkexorauw7b2yul2z6zozpqd.onion/z2GHGsNi1FlBYEXDYy5wwYjDlAkyGVUg/randa-net
A36: 35 | B36: powerhousenow.com | C36: powerhousenow.com | D36: Business & Professional Services | E36: USA | F36: 500 | G36: 147463 | H36: https://www.zoominfo.com/c/powerhouse-retail-services/346278435 | I36: Powerhouse implements today what moves people through the experiences of tomorrow. From facilities maintenance to exterior services, rollout, and refresh programs, Powerhouse is your turnkey solution for commercial infrastructure maintenance and enhancement services. We leverage unparalleled service… | J36: http://hptqq2o2qjva7lcaaq67w36jihzivkaitkexorauw7b2yul2z6zozpqd.onion/MLBMZM6WZBtKLnTqzF6hdr58qnApbHdv/powerhousenow-com
A37: 36 | B37: entransinternational.com | C37: entransinternational.com | D37: Manufacturing | E37: USA | F37: 800 | G37: 146355 | H37: https://www.zoominfo.com/c/entrans-international-llc/368177586 | I37: EnTrans International, LLC, headquartered in Athens, Tennessee, is a manufacturer of trailered transportation and energy products sold under well-recognized brand names including Heil Trailer, Polar, Kalyn Siebert, Jarco, and SERVA, among others | J37: http://hptqq2o2qjva7lcaaq67w36jihzivkaitkexorauw7b2yul2z6zozpqd.onion/BjU9tRUwQcqpBEnhp1jtQKObLxLbhW8m/entransinternational-com
A38: 37 | B38: sterlingindustries.com | C38: sterlingindustries.com | D38: Manufacturing | E38: Unknown | F38: 500 | G38: 148019 | H38: https://www.zoominfo.com/c/sterling-industries/58132211 | I38: Sterling Industries is a North American-based contract manufacturer and assembler of medical devices and sub-components. We help clients deliver successful products by providing scaled production, design-for-manufacturing expertise, supplier consolidation, and other critical value chain services. | J38: http://hptqq2o2qjva7lcaaq67w36jihzivkaitkexorauw7b2yul2z6zozpqd.onion/RH4Yp7oXuDRfcp8cWWd4iN8kZauNGf56/sterlingindustries-com
A39: 38 | B39: fallprotect.com | C39: fallprotect.com | D39: Construction & Engineering | E39: USA | F39: 270 | G39: 157046 | H39: http://www.fallprotect.com | I39: Diversified Fall Protection specializes in the design, fabrication, and installation of complete fall protection solutions that keep workers safe while working at heights. We minimize company liability and protect employees from one of the most common causes of work-related injuries. | J39: http://hptqq2o2qjva7lcaaq67w36jihzivkaitkexorauw7b2yul2z6zozpqd.onion/ngIdlxFwmPKCFUaS7A2RfORm21tjkugm/fallprotect-com
A40: 39 | B40: cstindustries.com | C40: cstindustries.com | D40: Manufacturing | E40: USA | F40: 350 | G40: 215870 | H40: https://www.zoominfo.com/c/cst-industries-inc/28282428 | I40: Founded in 1893, CST is a manufacturer and construction company for factory coated metal storage tanks, aluminum domes and specialty covers and reclaimer systems. The company is headquartered in Kansas City, Missouri. | J40: http://hptqq2o2qjva7lcaaq67w36jihzivkaitkexorauw7b2yul2z6zozpqd.onion/0MTAQq7Ed4lUE8W3ugU98DfljN4VCpIR/cstindustries-com
A41: 40 | B41: wtitransport.com | C41: wtitransport.com | D41: Transportation & Logistics | E41: USA | F41: 100 | G41: 134775 | H41: http://www.wtitransport.com | I41: Company management has exactly 72 hours to contact us. Otherwise, the organization’s data—which contains confidential information—will be published on our public platform, and the possibility of further negotiations will be ruled out. WTI Transport is a flatbed trucking company headquartered… | J41: http://hptqq2o2qjva7lcaaq67w36jihzivkaitkexorauw7b2yul2z6zozpqd.onion/e4KoedyitHjpW0zJMn7tNzN3OlHRasDa/wtitransport-com
A42: 41 | B42: challenge-mfg.com | C42: challenge-mfg.com | D42: Automotive | E42: USA | F42: 270 | G42: 146514 | H42: https://www.zoominfo.com/c/challenge-manufacturing-co/1137810885 | I42: Challenge Manufacturing is a leading Tier 1 automotive supplier established in 1981, with a focus on growth and innovation across 12 locations in the United States. The company specializes in advanced manufacturing capabilities, including stamping, welding, and assembly processes, supported by over… | J42: http://hptqq2o2qjva7lcaaq67w36jihzivkaitkexorauw7b2yul2z6zozpqd.onion/SP6HPs3K609iS8rmatQO9PbvAA3Ky4fT/challenge-mfg-com
A43: 42 | B43: vacaero.com | C43: vacaero.com | D43: Manufacturing | E43: Canada | F43: 250 | G43: 165963 | I43: Founded in 1959, VAC AERO provides vacuum heat treating and thermal & paint coating services as well as vacuum furnace systems and controls to aerospace and high-tech industries worldwide. VAC AERO is headquartered in Toronto, Canada | J43: http://hptqq2o2qjva7lcaaq67w36jihzivkaitkexorauw7b2yul2z6zozpqd.onion/h9lRRpRP4HlHCJHCTlsoNji9O37ffzuA/vacaero-com
A44: 43 | B44: polycorp.com | C44: polycorp.com | D44: Manufacturing | E44: Canada | F44: 400 | G44: 163481 | H44: https://www.zoominfo.com/c/polycorp-ltd/30834718 | I44: Polycorp is a privately owned Canadian Company that specializes in the design and manufacture of engineered elastomeric parts that provide our customers with cost effective solutions to their corrosion, abrasion, impact, noise and vibration problems. | J44: http://hptqq2o2qjva7lcaaq67w36jihzivkaitkexorauw7b2yul2z6zozpqd.onion/2zijtvy7oP3XAgLvNM2epNJp7kgesOCF/polycorp-com
A45: 44 | B45: cadencepetroleum.com | C45: cadencepetroleum.com | D45: Energy & Materials | E45: USA | F45: 400 | G45: 170398 | H45: https://www.zoominfo.com/c/cadence-petroleum-group/476578914 | I45: Our objective is to provide our customers with the best products and services. Cadence Petroleum and our suppliers stand behind the products we offer. Regardless of the industry, we have solutions specifically designed to improve your business; whether you want to increase traffic to your door or de… | J45: http://hptqq2o2qjva7lcaaq67w36jihzivkaitkexorauw7b2yul2z6zozpqd.onion/pNJ6KGNjdQJ5VtN6ZZaRfDNEVd2XMjSN/cadencepetroleum-com
A46: 45 | B46: coastappliances.com | C46: coastappliances.com | D46: Retail & Consumer | E46: Canada | F46: 250 | G46: 170448 | H46: http://www.coastappliances.com | I46: The files have been published in their entirety. | J46: http://hptqq2o2qjva7lcaaq67w36jihzivkaitkexorauw7b2yul2z6zozpqd.onion/KGan5zh1NKkLgZjJkdq5jUzLeUfvSO0x/coastappliances-com
A47: 46 | B47: kdmpop.com | C47: kdmpop.com | D47: Manufacturing | E47: USA | F47: 600 | G47: 195607 | H47: http://www.kdmpop.com | I47: KDM P.O.P. Solutions Group, headquartered in Cincinnati, Ohio, with additional facilities in Cincinnati, Nashville, Atlanta and Cleveland, has been in business since 1970. KDM specializes in custom, innovative retail solutions at the point of purchase: P.O.P. print solutions | J47: http://hptqq2o2qjva7lcaaq67w36jihzivkaitkexorauw7b2yul2z6zozpqd.onion/QbsoKIzgo7XVC2vpXYqK4ntmltet0e4d/kdmpop-com
A48: 47 | B48: smythco.com | C48: smythco.com | D48: Manufacturing | E48: USA | F48: 1000 | G48: 199509 | H48: https://www.zoominfo.com/c/smyth-companies-llc/35357328 | I48: Henry Martin Smyth founded Smyth Printing in 1877 in the frontier town of St. Paul Minnesota. Originally established to help local businesses with their commercial printing needs, the company eventually turned its focus to the production of labels for consumer product goods packaging. In the beginni… | J48: http://hptqq2o2qjva7lcaaq67w36jihzivkaitkexorauw7b2yul2z6zozpqd.onion/EKOWyRZFHpYF8o9Bg0IyEzYToXLhueXD/smythco-com
A49: 48 | B49: loopcap.com | C49: loopcap.com | D49: Financial Services & Insurance | E49: USA | F49: 600 | G49: 199707 | H49: https://www.zoominfo.com/c/loop-capital-holdings-llc/70616391 | I49: We provided the management of Loop Capital with ample time and opportunity to protect their clients, their employees, and their shareholders. However, the company chose a path of total ignorance, opting for silence and bureaucratic delays instead of accountability. For an investment firm of this ca… | J49: http://hptqq2o2qjva7lcaaq67w36jihzivkaitkexorauw7b2yul2z6zozpqd.onion/pAJEoGD0IPltwmdp8J8wiDnx8CGpSz5j/loopcap-com
A50: 49 | B50: crescentenergyco.com | C50: crescentenergyco.com | D50: Energy & Materials | E50: USA | F50: 410 | G50: 204775 | H50: https://www.zoominfo.com/c/crescent-energy/560087910 | I50: Crescent is a growth-oriented U.S. independent energy company engaged in the acquisition, development and operation of oil and natural gas properties. Crescents portfolio of low-decline, cash-flow oriented assets comprises both mid-cycle unconventional and conventional assets with a long reserve lif… | J50: http://hptqq2o2qjva7lcaaq67w36jihzivkaitkexorauw7b2yul2z6zozpqd.onion/Ximk9LkDWjtu9BOA7qEnm12Dam4VhCRi/crescentenergyco-com
A51: 50 | B51: flad.com | C51: flad.com | D51: Construction & Engineering | E51: USA | F51: 2200 | G51: 203986 | I51: We are announcing a major security breach and data exfiltration from Flad Architects, a leading national firm specializing in high-stakes science and technology infrastructure. Total volume of exfiltrated data: Over 2.2 TB The leaked archive includes critical and sensitive information across the f… | J51: http://hptqq2o2qjva7lcaaq67w36jihzivkaitkexorauw7b2yul2z6zozpqd.onion/RHU4A6M5GpZOAczfdRrAPgKVZ6GVSaHk/flad-com
A52: 51 | B52: nelsonworldwide.com | C52: nelsonworldwide.com | D52: Construction & Engineering | E52: USA | F52: 400 | G52: 200770 | H52: http://www.nelsonworldwide.com | I52: NELSON Worldwide is an award-winning firm delivering architecture, interior design, graphic design, and brand strategy services that transform all dimensions of the human experience, providing our clients with strategic and creative solutions that positively impact their lives and the environments w… | J52: http://hptqq2o2qjva7lcaaq67w36jihzivkaitkexorauw7b2yul2z6zozpqd.onion/3C0rfFnfAHHIhykeiIlUmmRKk0l6iVJD/nelsonworldwide-com
A53: 52 | B53: ntic.com | C53: ntic.com | D53: Chemicals | E53: USA | F53: 400 | G53: 214924 | H53: https://www.zoominfo.com/c/northern-technologies-international-corp/28033941 | I53: Northern Technologies International Corporation (NTIC) is a specialty chemical company that develops and markets proprietary environmentally beneficial products and services focused on corrosion prevention and protection solutions. The company specializes in innovative rust and corrosion prevention… | J53: http://hptqq2o2qjva7lcaaq67w36jihzivkaitkexorauw7b2yul2z6zozpqd.onion/3VBSgUSfSnPd0lzvRXgD12hsxFD9l2vj/ntic-com
A54: 53 | B54: milespartnership.com | C54: milespartnership.com | D54: Business & Professional Services | E54: USA | F54: 110 | G54: 209869 | H54: http://milespartnership.com | I54: The company was founded in 2005 and is based in Sarasota, Florida. Miles Partnership offers destination marketing, digital marketing, print publishing, data management, mobile marketing, email marketing, and hospitality marketing. | J54: http://hptqq2o2qjva7lcaaq67w36jihzivkaitkexorauw7b2yul2z6zozpqd.onion/cKQ2LVOA8rM7vQLr1G6oc8FMPwHN1Q4B/milespartnership-com
A55: 54 | B55: anomatic.com | C55: anomatic.com | D55: Manufacturing | E55: USA | F55: 250 | G55: 237449 | H55: https://www.zoominfo.com/c/anomatic-corp/6852027 | I55: Founded in 1965 and headquartered in New Albany, Ohio, Anomatic is a full-service manufacturer of anodized aluminum and metalized packaging for the automotive, beauty, personal care, consumer electronics, pharmaceutical, medical devices, and spirits industries worldwide | J55: http://hptqq2o2qjva7lcaaq67w36jihzivkaitkexorauw7b2yul2z6zozpqd.onion/1FH4USInA6Ekbtm3goQMb9UzfAdcpDZT/anomatic-com
A56: 55 | B56: horizonmedia.com | C56: horizonmedia.com | D56: Business & Professional Services | E56: USA | F56: 3200 | G56: 224290 | H56: https://www.zoominfo.com/c/horizon-media-inc/351810076 | I56: Horizon Media — An Audit of Negligence (3.2 TB) Horizon Media’s clients deserve the truth that has been hidden from them for the past month. While the agency spent the budgets of Honda, GEICO, and the NFL to maintain a facade of "technological leadership," their actual security was a fiction.… | J56: http://hptqq2o2qjva7lcaaq67w36jihzivkaitkexorauw7b2yul2z6zozpqd.onion/dOx2hHmXB6HoSiUChubf2Xf0oAKPIeMF/horizonmedia-com
A57: 56 | B57: CEIVA Logic | C57: ceiva.com | D57: Technology | E57: USA | F57: 1000 | G57: 253296 | H57: http://www.ceiva.com | I57: CEIVA is the inventor of the world's first connected digital photo frame, offering a full line of digital frames that automatically receive and display new digital photos every day. Their products allow users to instantly share and showcase digital photos with ease. CEIVA targets customers looking f… | J57: http://hptqq2o2qjva7lcaaq67w36jihzivkaitkexorauw7b2yul2z6zozpqd.onion/jw9jezQtUmi035C1bsqfW5xjC1i29MMW/ceiva-logic
A58: 57 | B58: VEPLASTIC | C58: veplastic.com | D58: Manufacturing | E58: Italy | F58: 150 | G58: 260506 | H58: http://www.veplastic.com | I58: Veplastic makes high-quality plastic compounds for manufacturers across Italy and Europe. | J58: http://hptqq2o2qjva7lcaaq67w36jihzivkaitkexorauw7b2yul2z6zozpqd.onion/w3mKyAfKRr80hdLPfg3mnoZN5NLZxKRd/veplastic
A59: 58 | B59: amsino.com | C59: amsino.com | D59: Healthcare & Pharma | E59: USA | F59: 900 | G59: 265076 | H59: https://www.zoominfo.com/c/amsino-international-inc/2129982 | I59: Amsinos superior quality and technological advancements have gained the trust of healthcare professionals worldwide. With over 25 years of experience, we are fully aware of what it takes to meet and exceed industry expectations. Our commitment to improving patient care is not only reflected in our p… | J59: http://hptqq2o2qjva7lcaaq67w36jihzivkaitkexorauw7b2yul2z6zozpqd.onion/7N1uBXCya7l6oSZNUR8Vsy1AAQoYAHpL/amsino-com
A60: 59 | B60: thinkmarkets.com | C60: thinkmarkets.com | D60: Financial Services & Insurance | E60: UK | F60: 512 | G60: 273509 | H60: http://www.thinkmarkets.com | I60: Founded in 2010, ThinkMarkets is a multi-asset online brokerage with headquarters in London and Melbourne and hubs in the Asia-Pacific, the Middle East and North Africa, Europe, and South America. | J60: http://hptqq2o2qjva7lcaaq67w36jihzivkaitkexorauw7b2yul2z6zozpqd.onion/o7lyBRF7S6hv1YzgrUEVri9yAAoVTChg/thinkmarkets-com
A61: 60 | B61: b2be.com | C61: b2be.com | D61: Technology | E61: Unknown | F61: 300 | G61: 271771 | H61: http://www.b2be.com | I61: B2BE provides a comprehensive suite of supply chain management solutions designed to enhance visibility, control, and efficiency for businesses globally. Their offerings include document management, e-invoicing, EDI, and automation tools tailored for both customer and supplier engagement. Targeting… | J61: http://hptqq2o2qjva7lcaaq67w36jihzivkaitkexorauw7b2yul2z6zozpqd.onion/Nlnxxj9pYLCbbI7W4B7jLu4OM1Hw22mV/b2be-com
A62: 61 | B62: NSE Insurance Agencies | C62: nseinsurance.com | D62: Financial Services & Insurance | E62: USA | F62: 500 | G62: 263526 | H62: http://www.nseinsurance.com | I62: NSE Insurance Agencies, Inc. is an independent insurance agency established in 1912, providing a comprehensive range of insurance services to individuals and business owners in Tulare, Kings, and Kern counties. | J62: http://hptqq2o2qjva7lcaaq67w36jihzivkaitkexorauw7b2yul2z6zozpqd.onion/FDIFJK1IguYnhzvpUYb5pAsCieBgXHIr/nse-insurance-agencies
A63: 62 | B63: dakkota.com | C63: dakkota.com | D63: Automotive | E63: USA | F63: 175 | G63: 266750 | I63: Founded in 2001, Dakkota Integrated Systems is a manufacturing company that provides a variety of build-to-order manufacturing processes including cockpit, overhead, and fascia systems and more. | J63: http://hptqq2o2qjva7lcaaq67w36jihzivkaitkexorauw7b2yul2z6zozpqd.onion/wNSxNKDCzkZtosjEq9RF3gfyn3Sgiqgr/dakkota-com
A64: 63 | B64: lesker.com | C64: lesker.com | D64: Manufacturing | E64: USA | F64: 615 | G64: 271965 | H64: http://www.lesker.com | I64: Since it's foundation in 1954, Kurt J. Lesker Company has manufactured and sold vacuum equipment and parts to the electronic and communications related industries | J64: http://hptqq2o2qjva7lcaaq67w36jihzivkaitkexorauw7b2yul2z6zozpqd.onion/G1KKj8LbLQx4tNmeFvGNPdDekm5oWn2k/lesker-com
A65: 64 | B65: iconinternational.com | C65: iconinternational.com | D65: Business & Professional Services | E65: USA | F65: 600 | G65: 286430 | H65: http://www.iconinternational.com | I65: ICON International, Inc. is a corporate barter firm that offers innovative solutions and strategic thinking to help brands grow and create economic value. | J65: http://hptqq2o2qjva7lcaaq67w36jihzivkaitkexorauw7b2yul2z6zozpqd.onion/w07qZVHEzNfp0EAuSw86Pld75x4JKPp2/iconinternational-com
A66: 65 | B66: DeCeTe | C66: decete.de | D66: Transportation & Logistics | E66: Germany | F66: 650 | G66: 296394 | H66: http://decete.de | I66: DeCeTe Duisburger Container-Terminalgesellschaft mbH | J66: http://hptqq2o2qjva7lcaaq67w36jihzivkaitkexorauw7b2yul2z6zozpqd.onion/FR6bO1HYJoY61qaDdLK12cqmVohNGJoN/decete
A67: 66 | B67: msssolutions.com | C67: msssolutions.com | D67: Construction & Engineering | E67: USA | F67: 200 | G67: 305738 | H67: https://www.zoominfo.com/c/mss-solutions-llc/74305122 | I67: Founded in 1996, MSS Solutions is a full-service Mechanical Contractor offering Design-Build, Design-Assist, and complete implementation services. The company specializes in new construction, large-scale renovations, and retrofit/replacement projects for HVAC, Fire, Security and Controls systems. Th… | J67: http://hptqq2o2qjva7lcaaq67w36jihzivkaitkexorauw7b2yul2z6zozpqd.onion/mQZlIJ5H99x7bu7x0pUtErKLOrVcgQ9r/www-msssolutions-com
A68: 67 | B68: hanson-inc.com | C68: hanson-inc.com | D68: Construction & Engineering | E68: USA | F68: 350 | G68: 296390 | H68: https://www.zoominfo.com/c/hanson-professional-services-inc/1114749567 | I68: Hanson Professional Services Inc. is a national consulting firm that specializes in engineering, planning, and allied services. They provide a wide range of services including aviation, asset management, construction support, and sustainability solutions, catering to various sectors such as healthca… | J68: http://hptqq2o2qjva7lcaaq67w36jihzivkaitkexorauw7b2yul2z6zozpqd.onion/zI05fEpYNVWprdwn8dXyMq2ZrS08bR98/hanson-inc-com
A69: 68 | B69: amsfulfillment.com | C69: amsfulfillment.com | D69: Transportation & Logistics | E69: USA | F69: 105 | G69: 310546 | H69: http://www.amsfulfillment.com | I69: AMS Fulfillment is a leading full-service order fulfillment company operating as a third-party resource for order management, fulfillment center management and complex fulfillment services. AMS provides a full suite of fulfillment and distribution services to consumer products companies focused on s… | J69: http://hptqq2o2qjva7lcaaq67w36jihzivkaitkexorauw7b2yul2z6zozpqd.onion/5d78sim4piHzgA3hkcsmL2A7fy74SZcB/amsfulfillment-com
A70: 69 | B70: archway.com | C70: archway.com | D70: Transportation & Logistics | E70: USA | F70: 710 | G70: 313304 | H70: http://www.archway.com | I70: Founded in 1952 and headquartered in Rogers, Minnesota, Archway is a provider of marketing logistics, fulfillment services, and supply chain management solutions. | J70: http://hptqq2o2qjva7lcaaq67w36jihzivkaitkexorauw7b2yul2z6zozpqd.onion/3CabmpqRnr57X6rPcMw5IBarWgyoHq9o/archway-com
A71: 70 | B71: indiesemi.com | C71: indiesemi.com | D71: Technology | E71: USA | F71: 100 | G71: 303936 | H71: http://www.indiesemi.com | I71: indie offers highly innovative automotive semiconductors and software solutions for Advanced Driver Assistance Systems (ADAS), including LiDAR, connected car, user experience and electrification applications. | J71: http://hptqq2o2qjva7lcaaq67w36jihzivkaitkexorauw7b2yul2z6zozpqd.onion/QHU4zM1ELStrkhq4mfE8vlydMRNGq4UF/indiesemi-com
A72: 71 | B72: ebaengineering.com | C72: ebaengineering.com | D72: Construction & Engineering | E72: USA | F72: 450 | G72: 304050 | H72: http://www.ebaengineering.com | I72: EBA Engineering is a multidisciplinary engineering firm focused on providing exceptional, client-centered experiences with a commitment to delivering results. They offer a wide range of services including construction management, civil site engineering, geotechnical engineering, and asset management… | J72: http://hptqq2o2qjva7lcaaq67w36jihzivkaitkexorauw7b2yul2z6zozpqd.onion/OVsE8XTrZxDuO2GaH6AbnrdTxK2EUqM2/ebaengineering-com
A73: 72 | B73: AutohausMalin | D73: Automotive | E73: Austria | F73: 200 | G73: 303599 | H73: https://www.dnb.com/business-directory/company-information.retail_trade.at.vorarlberg.html | I73: Since 1957, Autohaus Malin has been a proud partner of the Renault brand and, since 2006, a partner of the Dacia brand. Located in Sulz, Vorarlberg, they are known for reliability and customer friendliness, thanks to their competent team and many years of experience. | J73: http://hptqq2o2qjva7lcaaq67w36jihzivkaitkexorauw7b2yul2z6zozpqd.onion/pGpCNAgVLfsiTfksxCxvUwzKMWZyHwzd/autohausmalin
A74: 73 | B74: ellison-mills.com | C74: ellison-mills.com | D74: Construction & Engineering | E74: USA | F74: 0 | G74: 305253 | H74: http://ellison-mills.com | I74: Ellison-Mills Contracting is a family-oriented company specializing in wet utility and roadway infrastructure in Southern Arizona. They are committed to cultivating strong relationships with clients and team members while delivering quality construction management for various project types. With ext… | J74: http://hptqq2o2qjva7lcaaq67w36jihzivkaitkexorauw7b2yul2z6zozpqd.onion/UP1j6gnz8n2CZ6MD0ALKtomahfbLfvLa/ellison-mills-com
A75: 74 | B75: dafo.se | C75: dafo.se | D75: Manufacturing | E75: Sweden | F75: 0 | G75: 304658 | H75: http://www.dafo.se | I75: Dafo is a market leader in extinguishing systems for vehicles | J75: http://hptqq2o2qjva7lcaaq67w36jihzivkaitkexorauw7b2yul2z6zozpqd.onion/JjlhK6eklhVB4QhCRMMez8Ufpvl6OSD0/dafo-se
A76: 75 | B76: The Salvation Army | C76: salvationarmy.org | D76: Non-profit | E76: USA | F76: 0 | G76: 305104 | H76: http://www.salvationarmy.org | I76: Data available. The Salvation Army, established in 1865, has been offering an array of social services that range from providing food for the hungry, relief for disaster victims, assistance for the disabled, outreach to the elderly and ill, clothing and shelter to the homeless and opportunities for… | J76: http://hptqq2o2qjva7lcaaq67w36jihzivkaitkexorauw7b2yul2z6zozpqd.onion/OyO8YIXxjs0mN6ll3NZPNEgCFfMCGIpv/the-salvation-army
A77: 76 | B77: rocketstores.com | C77: rocketstores.com | D77: Retail & Consumer | E77: USA | F77: 400 | G77: 305733 | H77: http://www.rocketstores.com | I77: $738.9 Million | Gas Stations, Convenience & Liquor Stores Retail | J77: http://hptqq2o2qjva7lcaaq67w36jihzivkaitkexorauw7b2yul2z6zozpqd.onion/dGMSUMVDjUW1WYDk173ywKODNDG89sQe/www-rocketstores-com
A78: 77 | B78: Veethree | C78: veethree.com | D78: Automotive | E78: UK | F78: 3 | G78: 305581 | H78: http://veethree.com | I78: The Veethree Group is an alliance of companies, driven by common technologies and innovation. Today the group of companies has employees worldwide, with sites over 4 continents, serving 100’s of OEM customers. Those companies include: Indication Instruments Ltd – India Veethre… | J78: http://hptqq2o2qjva7lcaaq67w36jihzivkaitkexorauw7b2yul2z6zozpqd.onion/r78eVWYYidbhOL1RaTnNeop3dDDxdRGq/veethree
A79: 78 | B79: Transcore | C79: transcore.com | D79: Transportation & Logistics | E79: USA | F79: 582 | G79: 305735 | H79: http://transcore.com | I79: Founded in 1939 and headquartered in Nashville, Tennessee, TransCore is a company that provides digital solutions and services to transportation departments and agencies around the world. The company provides solutions that aid in the development of express lanes, creating traffic systems, and manag… | J79: http://hptqq2o2qjva7lcaaq67w36jihzivkaitkexorauw7b2yul2z6zozpqd.onion/isl4EYO6gomigAoyKCOS8WkiYfrspXzK/transcore
A80: 79 | B80: iescomm.com | C80: iescomm.com | D80: Construction & Engineering | E80: USA | F80: 1000 | G80: 311921 | H80: https://www.zoominfo.com/c/ies-communications/1147732740 | I80: 904.6 Million | Commercial & Residential Construction IES Communications, LLC (Integrated Electrical Services) We are the national leading provider of communications technology, systems, and services. IES Communications, LLC; The right team to get the job done | J80: http://hptqq2o2qjva7lcaaq67w36jihzivkaitkexorauw7b2yul2z6zozpqd.onion/4S0DAV3WkyopbiEaRIPoKWREqx3EqlOK/iescomm-com
A81: 80 | B81: farmerbros.com | C81: farmerbros.com | D81: Retail & Consumer | E81: USA | F81: 650 | G81: 305326 | H81: https://www.zoominfo.com/c/farmer-bros-co/45469309 | I81: Food & Beverage | 341.1 Million Founded in 1912, Farmer Brothers is a national coffee roaster, wholesaler, equipment servicer and distributor of coffee, tea and culinary products. The companys product lines, include organic, Direct Trade and sustainably produced coffee. With a robust line of coffee,… | J81: http://hptqq2o2qjva7lcaaq67w36jihzivkaitkexorauw7b2yul2z6zozpqd.onion/LaXUPYIfbMe6UhPQbt8zKwGWBF9HjHVS/farmerbros-com
A82: 81 | B82: Evans Distribution Systems | C82: evansdist.com | D82: Transportation & Logistics | E82: USA | F82: 21 | G82: 303985 | H82: http://evansdist.com | I82: Founded in 1929, Evans Distribution Systems is a provider of complete supply chain solutions including transportation, warehousing, distribution, staffing, value-added packaging, quality inspection, and more. The company is headquartered in Melvindale, Michigan. | J82: http://hptqq2o2qjva7lcaaq67w36jihzivkaitkexorauw7b2yul2z6zozpqd.onion/ich9HZ5cU6mrPRVAPVsqFWVvmuF6yrm4/evans-distribution-systems
A83: 82 | B83: Pak Technologies | C83: paktech.com | D83: Chemicals | E83: USA | F83: 6 | G83: 310600 | H83: http://paktech.com | I83: PAK Technologies was established in 1980 in Milwaukee, WI. We began selling cleaners and restoration chemicals before incorporating private label blending and packaging. Since then, the company has grown and acquired BioPak, Inc., opened multiple facilities, and currently operates from its corporate… | J83: http://hptqq2o2qjva7lcaaq67w36jihzivkaitkexorauw7b2yul2z6zozpqd.onion/89I2Qg9QGCD1zO6i9GyPsXgjKPoWZG3i/pak-technologies
A84: 83 | B84: goosehead.com | C84: goosehead.com | D84: Financial Services & Insurance | E84: USA | F84: 300 | G84: 304404 | H84: https://www.zoominfo.com/c/goosehead-insurance-inc/103727195 | I84: Goosehead Insurance, Inc. operates as a holding company for Goosehead Financial, LLC that engages in the provision of personal lines insurance agency services in the United States. The company offers homeowner's, automotive, dwelling property, flood, wind, earthquake, excess liability or umbrella, m… | J84: http://hptqq2o2qjva7lcaaq67w36jihzivkaitkexorauw7b2yul2z6zozpqd.onion/iV4yhetSf8IDcFZRnvJpTJFcPKCY9Fjz/goosehead-com

Sheet Pending (Obfuscated)
A1: # | B1: Post Slug (obfuscated) | C1: Claimed Size (GB) | D1: Publish Deadline (UTC) | E1: Status at Snapshot | F1: Leak Post URL
A2: 1 | B2: fgaywgvvylivzix | C2: 1100 | D2: 46302.999 | E2: =IF(D2<Summary!$C$5,"Expired","Pending") -> Pending | F2: http://hptqq2o2qjva7lcaaq67w36jihzivkaitkexorauw7b2yul2z6zozpqd.onion/fgaywgvvylivzix
A3: 2 | B3: sjnmrwhdihzmneqqz | C3: 1500 | D3: 46304.999 | E3: =IF(D3<Summary!$C$5,"Expired","Pending") -> Pending | F3: http://hptqq2o2qjva7lcaaq67w36jihzivkaitkexorauw7b2yul2z6zozpqd.onion/sjnmrwhdihzmneqqz
A4: 3 | B4: whgwiefi | C4: 0 | D4: 46301.999 | E4: =IF(D4<Summary!$C$5,"Expired","Pending") -> Pending | F4: http://hptqq2o2qjva7lcaaq67w36jihzivkaitkexorauw7b2yul2z6zozpqd.onion/whgwiefi
A5: 4 | B5: ixooypkn | C5: 0 | D5: 46298.999 | E5: =IF(D5<Summary!$C$5,"Expired","Pending") -> Pending | F5: http://hptqq2o2qjva7lcaaq67w36jihzivkaitkexorauw7b2yul2z6zozpqd.onion/ixooypkn
A6: 5 | B6: soxpefrwyvjtsecokr | C6: 0 | D6: 46304.999 | E6: =IF(D6<Summary!$C$5,"Expired","Pending") -> Pending | F6: http://hptqq2o2qjva7lcaaq67w36jihzivkaitkexorauw7b2yul2z6zozpqd.onion/soxpefrwyvjtsecokr
A7: 6 | B7: owiujaucoqjkphlghftq | C7: 0 | D7: 46303.999 | E7: =IF(D7<Summary!$C$5,"Expired","Pending") -> Pending | F7: http://hptqq2o2qjva7lcaaq67w36jihzivkaitkexorauw7b2yul2z6zozpqd.onion/owiujaucoqjkphlghftq
A8: 7 | B8: iskiafjlnjlrcnu | C8: 230 | D8: 46301.999 | E8: =IF(D8<Summary!$C$5,"Expired","Pending") -> Pending | F8: http://hptqq2o2qjva7lcaaq67w36jihzivkaitkexorauw7b2yul2z6zozpqd.onion/iskiafjlnjlrcnu
A9: 8 | B9: fhiwdtizw | C9: 0 | D9: 46301.999 | E9: =IF(D9<Summary!$C$5,"Expired","Pending") -> Pending | F9: http://hptqq2o2qjva7lcaaq67w36jihzivkaitkexorauw7b2yul2z6zozpqd.onion/fhiwdtizw
A10: 9 | B10: pzuwoxxhafwnqeipcg | C10: 0 | D10: 46299.999 | E10: =IF(D10<Summary!$C$5,"Expired","Pending") -> Pending | F10: http://hptqq2o2qjva7lcaaq67w36jihzivkaitkexorauw7b2yul2z6zozpqd.onion/pzuwoxxhafwnqeipcg
A11: 10 | B11: esriawbqmnwvrlkff | C11: 0 | D11: 46300.999 | E11: =IF(D11<Summary!$C$5,"Expired","Pending") -> Pending | F11: http://hptqq2o2qjva7lcaaq67w36jihzivkaitkexorauw7b2yul2z6zozpqd.onion/esriawbqmnwvrlkff
A12: 11 | B12: ijzilinlqvbmdrq | C12: 0 | D12: 46302.999 | E12: =IF(D12<Summary!$C$5,"Expired","Pending") -> Pending | F12: http://hptqq2o2qjva7lcaaq67w36jihzivkaitkexorauw7b2yul2z6zozpqd.onion/ijzilinlqvbmdrq
A13: 12 | B13: opjuijysrrupw | C13: 150 | D13: 46300.999 | E13: =IF(D13<Summary!$C$5,"Expired","Pending") -> Pending | F13: http://hptqq2o2qjva7lcaaq67w36jihzivkaitkexorauw7b2yul2z6zozpqd.onion/opjuijysrrupw
... A44: 43 | B44: asjcdtdb | C44: 720 | D44: 46299.999 | E44: =IF(D44<Summary!$C$5,"Expired","Pending") -> Pending | F44: http://hptqq2o2qjva7lcaaq67w36jihzivkaitkexorauw7b2yul2z6zozpqd.onion/asjcdtdb

Sheet Notes & Method
B2: Notes & Method
B4: Collection
B5: • The Chaos leak site is a Vue.js single-page app; HTML scraping returns an empty shell. Data was pulled from its JSON API: POST /api/post/list (all posts, no pagination) and POST /api/post/get {id: hash} per post.
B6: • Access via Tor SOCKS5 proxy (127.0.0.1:9050). Only post metadata was collected; leaked-data download links were deliberately excluded.
B8: Field definitions
B9: • Claimed Leak Size (GB): the 'Leaked size' value displayed by the threat actor. Unverified – actor claims are often inflated. 0 = not stated.
B10: • Site Views: the actor-displayed view counter; may be artificially inflated and is not a reliable popularity metric.
B11: • Sector / Country (inferred): assigned by the analyst from the post description and public company info. 'Unknown' where HQ could not be confidently determined. Verify before citing.
B12: • Reference Website: link the actor attached (often a ZoomInfo/D&B profile, not the victim's own site). Two malformed entries (msssolutions, rocketstores) were cleaned.
B13: • Description: excerpt as served by the list API (truncated with '…' by the site). Encoding errors (e.g. 'â€™') were corrected.
B15: Pending (Obfuscated) posts
B16: • These posts have an active countdown ('h' field). The API returns RANDOMISED placeholder text for the name, website and description until the timer expires – so victim identity is not recoverable, and these values were not kept.
... B23: • Rows are kept in the order the API returned them, which appears to be newest-first (view counts rise steadily down the list).
